nlpnet/__init__.py
nlpnet/arguments.py
nlpnet/attributes.py
nlpnet/config.py
nlpnet/metadata.py
nlpnet/network.cpython-37m-darwin.so
nlpnet/reader.py
nlpnet/taggers.py
nlpnet/utils.py
nlpnet/word_dictionary.py
nlpnet/parse/__init__.py
nlpnet/parse/parse_reader.py
nlpnet/pos/__init__.py
nlpnet/pos/macmorphoreader.py
nlpnet/pos/pos_reader.py
nlpnet/srl/__init__.py
nlpnet/srl/srl_reader.py
nlpnet/srl/train_srl.py
nlpnet-1.2.4.data/scripts/nlpnet-load-embeddings.py
nlpnet-1.2.4.data/scripts/nlpnet-tag.py
nlpnet-1.2.4.data/scripts/nlpnet-test.py
nlpnet-1.2.4.data/scripts/nlpnet-train.py
nlpnet-1.2.4.dist-info/LICENSE.txt
nlpnet-1.2.4.dist-info/METADATA
nlpnet-1.2.4.dist-info/WHEEL
nlpnet-1.2.4.dist-info/top_level.txt
nlpnet-1.2.4.dist-info/RECORD
