Metadata-Version: 2.1
Name: nlpnet
Version: 1.2.4
Summary: Neural networks for NLP tasks
Home-page: http://nilc.icmc.usp.br/nlpnet
Author: Erick Fonseca
Author-email: erickrfonseca@gmail.com
License: MIT
Platform: UNKNOWN
Requires-Dist: numpy (>=1.9.0)
Requires-Dist: nltk (>=3.2.2)
Requires-Dist: six (>=1.10)
Requires-Dist: h5py (>=2.8.0rc1)
